LICENSE
LISENSI
README-EN.md
README.md
dapodik/__init__.py
dapodik/__main__.py
dapodik/auth/__init__.py
dapodik/auth/base.py
dapodik/auth/pengguna.py
dapodik/base.py
dapodik/beranda/__init__.py
dapodik/beranda/base.py
dapodik/beranda/info_survey_ptm.py
dapodik/beranda/kerusakan_bangunan.py
dapodik/beranda/panel_dashboard.py
dapodik/constants.py
dapodik/customrest/__init__.py
dapodik/customrest/base.py
dapodik/customrest/wilayah.py
dapodik/dapodik.py
dapodik/enums.py
dapodik/exception.py
dapodik/gtk/__init__.py
dapodik/gtk/base.py
dapodik/gtk/enums.py
dapodik/gtk/ptk.py
dapodik/gtk/ptk_terdaftar.py
dapodik/message.py
dapodik/peserta_didik/__init__.py
dapodik/peserta_didik/base.py
dapodik/peserta_didik/create_peserta_didik.py
dapodik/peserta_didik/peserta_didik.py
dapodik/peserta_didik/peserta_didik_baru.py
dapodik/peserta_didik/peserta_didik_longitudinal.py
dapodik/peserta_didik/registrasi_peserta_didik.py
dapodik/response.py
dapodik/rest/__init__.py
dapodik/rest/agama.py
dapodik/rest/akreditasi.py
dapodik/rest/akses_internet.py
dapodik/rest/alasan_layak_pip.py
dapodik/rest/alat_transportasi.py
dapodik/rest/bank.py
dapodik/rest/base.py
dapodik/rest/bentuk_lembaga.py
dapodik/rest/biblio.py
dapodik/rest/child_delete.py
dapodik/rest/fasilitas_layanan.py
dapodik/rest/gmd.py
dapodik/rest/jadwal_paud.py
dapodik/rest/jenis_cita.py
dapodik/rest/jenis_gugus.py
dapodik/rest/jenis_hapus_buku.py
dapodik/rest/jenis_hobby.py
dapodik/rest/jenis_keluar.py
dapodik/rest/jenis_lk.py
dapodik/rest/jenis_pendaftaran.py
dapodik/rest/jenis_prasarana.py
dapodik/rest/jenis_ptk.py
dapodik/rest/jenis_rombel.py
dapodik/rest/jenis_sarana.py
dapodik/rest/jenis_tinggal.py
dapodik/rest/jenjang_pendidikan.py
dapodik/rest/jurusan.py
dapodik/rest/kategori_tk.py
dapodik/rest/keahlian_laboratorium.py
dapodik/rest/kebutuhan_khusus.py
dapodik/rest/klasifikasi_lembaga.py
dapodik/rest/kurikulum.py
dapodik/rest/lembaga_pengangkat.py
dapodik/rest/mata_pelajaran.py
dapodik/rest/mst_wilayah.py
dapodik-0.19.0.dist-info/LICENSE
dapodik-0.19.0.dist-info/METADATA
dapodik-0.19.0.dist-info/WHEEL
dapodik-0.19.0.dist-info/entry_points.txt
dapodik-0.19.0.dist-info/RECORD
