Metadata-Version: 2.1
Name: dapodik
Version: 0.19.0
Summary: SDK python untuk aplikasi dapodik.
Home-page: https://dapodix.github.io/dapodik
License: MIT
Keywords: dapodik,kemdikbud,python-module,python-sdk,python-wrapper
Author: hexatester
Author-email: habibrohman@protonmail.com
Requires-Python: >=3.7,<4.0
Classifier: Development Status :: 4 - Beta
Classifier: Intended Audience :: Developers
Classifier: License :: OSI Approved :: MIT License
Classifier: Operating System :: OS Independent
Classifier: Programming Language :: Python :: 3
Classifier: Programming Language :: Python :: 3.7
Classifier: Programming Language :: Python :: 3.8
Classifier: Programming Language :: Python :: 3.9
Classifier: Programming Language :: Python :: 3.10
Classifier: Programming Language :: Python :: 3.11
Classifier: Topic :: Education
Provides-Extra: ujson
Requires-Dist: attrs (>=21.0.0,<=23.0.0)
Requires-Dist: beautifulsoup4 (>=4.0.0)
Requires-Dist: cachetools (>=4.2.2,<5.0.0)
Requires-Dist: cattrs (>=21.0.0,<=23.0.0)
Requires-Dist: requests (>=2.0.0)
Requires-Dist: ujson (>=5.7.0,<6.0.0) ; extra == "ujson"
Project-URL: Documentation, https://github.com/dapodix/dapodik/wiki
Project-URL: Repository, https://github.com/hexatester/dapodik
